llama_index/agent/openai/__init__.py
llama_index/agent/openai/base.py
llama_index/agent/openai/openai_assistant_agent.py
llama_index/agent/openai/step.py
llama_index/agent/openai/utils.py
basejump_llama_index_agent_openai-0.4.7.post1.dist-info/METADATA
basejump_llama_index_agent_openai-0.4.7.post1.dist-info/WHEEL
basejump_llama_index_agent_openai-0.4.7.post1.dist-info/licenses/LICENSE
basejump_llama_index_agent_openai-0.4.7.post1.dist-info/RECORD
