Metadata-Version: 2.4
Name: basejump-llama-index-agent-openai
Version: 0.4.7.post1
Summary: llama-index agent openai integration
Author-email: Your Name <you@example.com>
License-Expression: MIT
License-File: LICENSE
Requires-Python: <4.0,>=3.9
Requires-Dist: basejump-llama-index-core<0.13,>=0.12.18
Requires-Dist: basejump-llama-index-llms-openai<0.4,>=0.3.0
Requires-Dist: openai>=1.14.0
